<Lut name="CT_Clr_abd_aorta_1">
  <Color Interpolation="RGB">
    <Point>
      <Index>80.9</Index>
      <R>130</R>
      <G>255</G>
      <B>93</B>
    </Point>
    <Point>
      <Index>136</Index>
      <R>255</R>
      <G>204</G>
      <B>98</B>
    </Point>
    <Point>
      <Index>225.8</Index>
      <R>255</R>
      <G>64</G>
      <B>64</B>
    </Point>
    <Point>
      <Index>401.3</Index>
      <R>255</R>
      <G>254</G>
      <B>243</B>
    </Point>
    <Point>
      <Index>803</Index>
      <R>255</R>
      <G>254</G>
      <B>243</B>
    </Point>
  </Color>
  <Opacity>
    <Point>
      <Index>80.9</Index>
      <A>0</A>
    </Point>
    <Point>
      <Index>87</Index>
      <A>0</A>
    </Point>
    <Point>
      <Index>803</Index>
      <A>255</A>
    </Point>
  </Opacity>
  <WindowLevel>
    <Width>712.1</Width>
    <Level>441.95</Level>
  </WindowLevel>
  <Background>
    <R>0</R>
    <G>0</G>
    <B>0</B>
    <A>1</A>
  </Background>
  <Material>
    <DiffuseColor>
      <R>255</R>
      <G>255</G>
      <B>255</B>
      <Factor>0.5</Factor>
    </DiffuseColor>
    <SpecularColor>
      <R>255</R>
      <G>255</G>
      <B>255</B>
      <Factor>0.5</Factor>
      <Shininess>2</Shininess>
    </SpecularColor>
  </Material>
</Lut>
